matflow_demo_extension/__init__.py
matflow_demo_extension/_version.py
matflow_demo_extension/main.py
matflow_demo_extension-0.1.3.dist-info/LICENSE
matflow_demo_extension-0.1.3.dist-info/METADATA
matflow_demo_extension-0.1.3.dist-info/WHEEL
matflow_demo_extension-0.1.3.dist-info/entry_points.txt
matflow_demo_extension-0.1.3.dist-info/top_level.txt
matflow_demo_extension-0.1.3.dist-info/zip-safe
matflow_demo_extension-0.1.3.dist-info/RECORD
